cshopify/__init__.py
cshopify/api.py
shopify_custom_api-0.1.3.dist-info/LICENSE.txt
shopify_custom_api-0.1.3.dist-info/METADATA
shopify_custom_api-0.1.3.dist-info/WHEEL
shopify_custom_api-0.1.3.dist-info/top_level.txt
shopify_custom_api-0.1.3.dist-info/RECORD
