Metadata-Version: 2.1
Name: shopify_custom_api
Version: 0.1.3
Summary: A simple library that helps call Shopify's API
Home-page: https://github.com/bachnguyen2001/shopify_custom_api.git
Author: Nguyen Ngoc Bach
Author-email: bachnguyenfptu@gmail.com
License: MIT
Keywords: shopify rest api
Classifier: Programming Language :: Python :: 3
Classifier: License :: OSI Approved :: MIT License
Classifier: Operating System :: OS Independent
Requires-Python: >=3.10
License-File: LICENSE.txt
Requires-Dist: requests
